tencentcloud/__init__.py
tencentcloud/tsw/__init__.py
tencentcloud/tsw/v20200924/__init__.py
tencentcloud/tsw/v20200924/errorcodes.py
tencentcloud/tsw/v20200924/models.py
tencentcloud/tsw/v20200924/tsw_client.py
tencentcloud/tsw/v20210412/__init__.py
tencentcloud/tsw/v20210412/errorcodes.py
tencentcloud/tsw/v20210412/models.py
tencentcloud/tsw/v20210412/tsw_client.py
tencentcloud_sdk_python_tsw-3.0.1459.dist-info/METADATA
tencentcloud_sdk_python_tsw-3.0.1459.dist-info/WHEEL
tencentcloud_sdk_python_tsw-3.0.1459.dist-info/top_level.txt
tencentcloud_sdk_python_tsw-3.0.1459.dist-info/RECORD
